{
    "samples per pixel (0 means no antialiasing)": 0,
    "png output": "scene.png",
    "camera": {
        "distance": 1.0,
        "aspect ratio": 1.0,
        "transformation": [
            [
                1.0,
                0.0,
                0.0,
                0.0
            ],
            [
                0.0,
                1.0,
                0.0,
                0.0
            ],
            [
                0.0,
                0.0,
                1.0,
                0.0
            ],
            [
                -3.0,
                0.0,
                1.0,
                1.0
            ]
        ],
        "projection": "orthogonal"
    },
    "tonemapping": {
        "input average luminosity": 0.05,
        "gamma": 1.0,
        "normalization": 0.18
    },
    "declared float from Command Line": null,
    "scene file": "examples/earth_moon_sun.txt",
    "renderer": {
        "algorithm": "Point-Light Renderer",
        "background color": {
            "r": 0.0,
            "g": 0.0,
            "b": 0.0
        },
        "color": {
            "r": 0.0,
            "g": 0.0,
            "b": 0.0
        }
    },
    "rendering time (in s)": "5.761",
    "time of start": "2021-6-28 : 13:7:58",
    "pfm output": "scene.pfm"
}
